{
	"configurations" : 
	[
		{
			"directories" : 
			[
				{
					"build" : ".",
					"hasInstallRule" : true,
					"jsonFile" : "directory-.-a15ff3a26e88f8180d33.json",
					"minimumCMakeVersion" : 
					{
						"string" : "3.15"
					},
					"projectIndex" : 0,
					"source" : ".",
					"targetIndexes" : 
					[
						0,
						1,
						2
					]
				}
			],
			"name" : "",
			"projects" : 
			[
				{
					"directoryIndexes" : 
					[
						0
					],
					"name" : "roam_bot",
					"targetIndexes" : 
					[
						0,
						1,
						2
					]
				}
			],
			"targets" : 
			[
				{
					"directoryIndex" : 0,
					"id" : "roam_bot::@6890427a1f51a3e7e1df",
					"jsonFile" : "target-roam_bot-56ce2c11a04b553c07a3.json",
					"name" : "roam_bot",
					"projectIndex" : 0
				},
				{
					"directoryIndex" : 0,
					"id" : "roam_bot_uninstall::@6890427a1f51a3e7e1df",
					"jsonFile" : "target-roam_bot_uninstall-939c0a395aa3f6e990aa.json",
					"name" : "roam_bot_uninstall",
					"projectIndex" : 0
				},
				{
					"directoryIndex" : 0,
					"id" : "uninstall::@6890427a1f51a3e7e1df",
					"jsonFile" : "target-uninstall-e368e9d0f699923c045a.json",
					"name" : "uninstall",
					"projectIndex" : 0
				}
			]
		}
	],
	"kind" : "codemodel",
	"paths" : 
	{
		"build" : "/home/ros2_senior/Senior-Design/ros2_roam_bot/build/roam_bot",
		"source" : "/home/ros2_senior/Senior-Design/ros2_roam_bot/src/ros2_control_demos/example_2"
	},
	"version" : 
	{
		"major" : 2,
		"minor" : 6
	}
}
